swiftmcp.cpython-312-darwin.so
swiftmcp.cpython-313-darwin.so
swiftmcp.pyi
swiftmcp-0.0.5.dist-info/RECORD
swiftmcp-0.0.5.dist-info/WHEEL
swiftmcp-0.0.5.dist-info/entry_points.txt
swiftmcp-0.0.5.dist-info/top_level.txt
swiftmcp-0.0.5.dist-info/METADATA
swiftmcp-0.0.5.dist-info/licenses/LICENSE
