Metadata-Version: 2.4
Name: swiftmcp
Version: 0.0.5
Summary: multimoda MCP framework
Author-email: Yaqiang Sun <sunyaking@163.com>
License: GPL-3.0
Requires-Python: <3.14,>=3.12
License-File: LICENSE
Requires-Dist: fastapi>=0.121.0
Requires-Dist: fastmcp>=2.13.0.2
Requires-Dist: miniolite>=0.0.0.3
Dynamic: license-file
